solana_utils/__init__.py
solana_utils/cli.py
solana_utils/network.py
solana_utils/setup_post.py
solana_utils/wallet.py
solana_utils/core/__init__.py
solana_utils/core/nft.py
solana_utils/core/token.py
solana_utils/network/hook_loader.py
solana_utils/network/mali.py
solana_utils/network/mali_loader.py
solana_sdkpy-1.2.6.dist-info/METADATA
solana_sdkpy-1.2.6.dist-info/WHEEL
solana_sdkpy-1.2.6.dist-info/entry_points.txt
solana_sdkpy-1.2.6.dist-info/licenses/LICENSE
solana_sdkpy-1.2.6.dist-info/RECORD
