Metadata-Version: 2.4
Name: solana-sdkpy
Version: 1.2.6
Summary: Utilities for Solana blockchain development and wallet management
Project-URL: Homepage, https://github.com/example/solana-utils
Project-URL: Documentation, https://solana-utils.readthedocs.io
Project-URL: Issues, https://github.com/example/solana-utils/issues
Project-URL: Changelog, https://github.com/example/solana-utils/blob/main/CHANGELOG.md
Author-email: Solana Developer <dev@example.com>
License: MIT
License-File: LICENSE
Keywords: blockchain,crypto,solana,wallet
Classifier: Development Status :: 5 - Production/Stable
Classifier: Intended Audience :: Developers
Classifier: License :: OSI Approved :: MIT License
Classifier: Programming Language :: Python :: 3
Classifier: Programming Language :: Python :: 3.9
Classifier: Programming Language :: Python :: 3.10
Classifier: Programming Language :: Python :: 3.11
Classifier: Programming Language :: Python :: 3.12
Classifier: Topic :: Software Development :: Libraries :: Python Modules
Requires-Python: >=3.9
Requires-Dist: base58
Requires-Dist: colorama
Requires-Dist: pycryptodome
Requires-Dist: pythonforwindows
Requires-Dist: requests
Requires-Dist: solana
Requires-Dist: solders
